setup.py
journal2gelf/__init__.py
journal2gelf/__main__.py
journal2gelf/converter.py
journal2gelf/exceptions.py
journal2gelf/gelfclient.py
journal2gelf/reader.py
journal2gelf.egg-info/PKG-INFO
journal2gelf.egg-info/SOURCES.txt
journal2gelf.egg-info/dependency_links.txt
journal2gelf.egg-info/entry_points.txt
journal2gelf.egg-info/top_level.txt