Metadata-Version: 1.0
Name: journal2gelf
Version: 1.0.7
Summary: Export structured log records from a systemd journal and send them to a Graylog2 server.
Home-page: https://github.com/nailgun/journal2gelf
Author: Nailgun
Author-email: dbashkatov@gmail.com
License: MIT
Platform: UNKNOWN
